bond_async/__init__.py
bond_async/action.py
bond_async/bond.py
bond_async/bond_type.py
bond_async/bpup.py
bond_async/device_type.py
bond_async/requestor_uuid.py
bond_async-0.2.1.dist-info/LICENSE
bond_async-0.2.1.dist-info/METADATA
bond_async-0.2.1.dist-info/WHEEL
bond_async-0.2.1.dist-info/top_level.txt
bond_async-0.2.1.dist-info/RECORD
