Metadata-Version: 2.1
Name: bond_async
Version: 0.2.1
Summary: Asynchronous Python wrapper library over Bond Local API
Home-page: https://github.com/bondhome/bond-async
Author: Olibra LLC
Author-email: mobiledev@olibra.io
License: MIT
Keywords: bond local api async
Classifier: Intended Audience :: Developers
Classifier: License :: OSI Approved :: MIT License
Classifier: Operating System :: OS Independent
Classifier: Programming Language :: Python :: 3.7
Classifier: Topic :: Home Automation
License-File: LICENSE
